[
  {
    "version": "1.21.4",
    "changes": [
      {
        "date": "2026-06-11T00:11:28.563Z",
        "node": "",
        "commit": "**MK Cables**: Add endpoint swinging."
      }
    ]
  },
  {
    "version": "1.21.2.007",
    "changes": [
      {
        "date": "2026-05-28T07:53:51.720Z",
        "node": "Animation Panel",
        "commit": "**Animation Panel**: Add easing hotkey (E)."
      }
    ]
  },
  {
    "version": "1.21.2.006",
    "changes": [
      {
        "date": "2026-05-27T01:14:10.253Z",
        "node": "",
        "commit": "**Path Fill / Map / Revolve / SDF**: Add transform, path range properties."
      },
      {
        "date": "2026-05-27T01:14:10.257Z",
        "node": "",
        "commit": "**Path Fill / Map / Revolve / SDF**: Add transform, path range properties."
      }
    ]
  },
  {
    "version": "1.21.0.2.004",
    "changes": [
      {
        "date": "2026-05-05T04:36:04.382Z",
        "node": "",
        "commit": "**Graph Panel**: Fix crash when trying to blend nodes with no surface output."
      }
    ]
  }
]