[
  {
    "version": "1.21.7.103",
    "changes": [
      {
        "date": "2026-07-19T03:11:15.168Z",
        "node": "",
        "commit": "Fix non-uniform surface tiled incorrectly."
      }
    ]
  },
  {
    "version": "1.21.5",
    "changes": [
      {
        "date": "2026-06-22T01:01:52.165Z",
        "node": "",
        "commit": "**Transform**: Fix crash when setting animation frame to less than 1."
      }
    ]
  },
  {
    "version": "1.21.4.009",
    "changes": [
      {
        "date": "2026-06-19T07:23:58.250Z",
        "node": "",
        "commit": "**Transform**: Add path input."
      },
      {
        "date": "2026-06-19T07:39:24.615Z",
        "node": "Inspector Panel",
        "commit": "**Inspector Panel**: Dropping value to another value now create expression."
      }
    ]
  },
  {
    "version": "1.21.4.008",
    "changes": [
      {
        "date": "2026-06-18T02:00:16.571Z",
        "node": "",
        "commit": "Add more quick anim presets."
      }
    ]
  },
  {
    "version": "1.21.3.009",
    "changes": [
      {
        "date": "2026-06-09T04:15:28.315Z",
        "node": "",
        "commit": "**Bend**: Add UV position, scale properties."
      },
      {
        "date": "2026-06-09T04:22:56.320Z",
        "node": "Transform",
        "commit": "**Transform**: Add echo blend modes."
      }
    ]
  },
  {
    "version": "1.21.2.008",
    "changes": [
      {
        "date": "2026-05-29T10:04:43.596Z",
        "node": "",
        "commit": "**Transform, Repeat, Scatter, Particle**: Add Clean Edge interpolation algorithm."
      }
    ]
  },
  {
    "version": "1.21.1.010",
    "changes": [
      {
        "date": "2026-05-20T02:57:10.665Z",
        "node": "",
        "commit": "**Offset**: Add offset angle control."
      }
    ]
  },
  {
    "version": "1.21.1.007",
    "changes": [
      {
        "date": "2026-05-18T06:36:00.542Z",
        "node": "",
        "commit": "Add quick action pie menu to some nodes."
      }
    ]
  }
]